{"ราคา": "329,000 บาท", "ประเภท": "Sedan\n", "รูป": "https://img4.icarcdn.com/9006307/gallery_used-car-one2car-honda-civic-s-i-vtec-sedan-thailand_FBD00CE6DDC94881B46A512145F9672D_9006307_2umNFRcMaYbklvJYJViNdQ.jpg?smia=xTM", "\n\nดีลเลอร์มีความน่าเชื่อถือ ผ่านการตรวจสอบตามเกณฑ์ที่กำหนด\n": "ดีลเลอร์มีความน่าเชื่อถือ ผ่านการตรวจสอบตามเกณฑ์ที่กำหนด", "ยี่ห้อ": "Honda", "รุ่น": "Civic", "โฉมรถยนต์": "FD (ปี 05-12)", "รายละเอียดรุ่น": "S i-VTEC", "ปี": "2010", "ขนาดเครื่องยนต์": "1799 ซีซี", "ระบบเกียร์": "เกียร์อัตโนมัติ", "จำนวนที่นั่ง": "5", "เลขไมล์ (กม.)": "100 - 105K", "สี": "สีเทา"}