{"ราคา": "499,000 บาท", "ประเภท": "Pickup\n", "รูป": "https://img5.icarcdn.com/0699117/gallery_used-car-one2car-toyota-hilux-revo-prerunner-e-plus-pickup-thailand_0699117_5dFkGJ22630pwBRmmuF31J.jpg?smia=xTM", "\n\nดีลเลอร์มีความน่าเชื่อถือ ผ่านการตรวจสอบตามเกณฑ์ที่กำหนด\n": "ดีลเลอร์มีความน่าเชื่อถือ ผ่านการตรวจสอบตามเกณฑ์ที่กำหนด", "ยี่ห้อ": "Toyota", "รุ่น": "Hilux Revo", "โฉมรถยนต์": "SMARTCAB", "รายละเอียดรุ่น": "Prerunner E Plus", "ปี": "2017", "ขนาดเครื่องยนต์": "2393 ซีซี", "ระบบเกียร์": "เกียร์อัตโนมัติ", "จำนวนที่นั่ง": "2", "เลขไมล์ (กม.)": "135 - 140K", "สี": "สีขาว"}