{"ราคา": "529,000 บาท", "ประเภท": "Pickup\n", "รูป": "https://img3.icarcdn.com/3843917/gallery_used-car-one2car-toyota-hilux-revo-prerunner-e-pickup-thailand_942c5753b87a4e8b49a4f1f3f8436262_NuSuzSuMCRN3QksPd20pah_3843917_BUhmc77FuAxG2tlmn5KAnd.jpg?smia=xTM", "\n\nดีลเลอร์มีความน่าเชื่อถือ ผ่านการตรวจสอบตามเกณฑ์ที่กำหนด\n": "ดีลเลอร์มีความน่าเชื่อถือ ผ่านการตรวจสอบตามเกณฑ์ที่กำหนด", "ยี่ห้อ": "Toyota", "รุ่น": "Hilux Revo", "โฉมรถยนต์": "DOUBLE CAB", "รายละเอียดรุ่น": "Prerunner E", "ปี": "2015", "ขนาดเครื่องยนต์": "2393 ซีซี", "ระบบเกียร์": "เกียร์อัตโนมัติ", "จำนวนที่นั่ง": "5", "เลขไมล์ (กม.)": "130 - 135K", "สี": "สีเทา"}