{"ราคา": "549,000 บาท", "ประเภท": "...\n", "รูป": "https://img3.icarcdn.com/7692527/gallery_used-car-one2car-isuzu-d-max-hi-lander-z-prestige-pickup-thailand_7692527_b2DZAO2EAMAXS3kZiGIOpm.jpg?smia=xTM", "\n\nดีลเลอร์มีความน่าเชื่อถือ ผ่านการตรวจสอบตามเกณฑ์ที่กำหนด\n": "ดีลเลอร์มีความน่าเชื่อถือ ผ่านการตรวจสอบตามเกณฑ์ที่กำหนด", "ยี่ห้อ": "Isuzu", "รุ่น": "D-Max", "โฉมรถยนต์": "CAB-4 (ปี 11-17)", "รายละเอียดรุ่น": "Hi-Lander Z-Prestige", "ปี": "2015", "ขนาดเครื่องยนต์": "2999 ซีซี", "ระบบเกียร์": "เกียร์อัตโนมัติ", "จำนวนที่นั่ง": "5", "เลขไมล์ (กม.)": "80000", "สี": "สีขาว", "สถานที่": "isuzu-d-max-hi-lander-z-prestige-กรุงเทพและปริมณฑล-กาญจนาภิเษก", "ลิงก์": "https://www.one2car.com/for-sale/isuzu-d-max-hi-lander-z-prestige-กรุงเทพและปริมณฑล-กาญจนาภิเษก/7252967"}