{"ราคา": "6,000,000 บาท", "ประเภท": "AT\n", "รูป": "https://img4.icarcdn.com/1974527/gallery_used-car-one2car-bmw-m-m5-sedan-thailand_1974527_eqc9dVnvZds4iRZK0zMN2t.jpg?smia=xTM", "\n\nดีลเลอร์มีความน่าเชื่อถือ ผ่านการตรวจสอบตามเกณฑ์ที่กำหนด\n": "", "ยี่ห้อ": "BMW", "รุ่น": "M5", "โฉมรถยนต์": "F10 (ปี 11-16)", "รายละเอียดรุ่น": "", "ปี": "2012", "ขนาดเครื่องยนต์": "4395 ซีซี", "ระบบเกียร์": "เกียร์อัตโนมัติ", "จำนวนที่นั่ง": "5", "เลขไมล์ (กม.)": "45 - 50K", "สี": "สีขาว", "สถานที่": "bmw-m5-กรุงเทพและปริมณฑล-บางนา-กิ่งแก้ว-ลาดกระบัง", "ลิงก์": "https://www.one2car.com/for-sale/bmw-m5-กรุงเทพและปริมณฑล-บางนา-กิ่งแก้ว-ลาดกระบัง/7254791"}