{"ราคา": "318,000 บาท", "ประเภท": "Hatchback\n", "รูป": "https://img4.icarcdn.com/3184527/gallery_used-car-one2car-honda-jazz-hybrid-hatchback-thailand_3184527_ddG6FW2gf6ESyj42FJtFMR.jpg?smia=xTM", "\n\nดีลเลอร์มีความน่าเชื่อถือ ผ่านการตรวจสอบตามเกณฑ์ที่กำหนด\n": "ดีลเลอร์มีความน่าเชื่อถือ ผ่านการตรวจสอบตามเกณฑ์ที่กำหนด", "ยี่ห้อ": "Honda", "รุ่น": "Jazz", "โฉมรถยนต์": "(ปี 08-14)", "รายละเอียดรุ่น": "Hybrid", "ปี": "2013", "ขนาดเครื่องยนต์": "1339 ซีซี", "ระบบเกียร์": "เกียร์อัตโนมัติ", "จำนวนที่นั่ง": "5", "เลขไมล์ (กม.)": "2500", "สี": "สีขาว", "สถานที่": "honda-jazz-hybrid-กรุงเทพและปริมณฑล-กาญจนาภิเษก", "ลิงก์": "https://www.one2car.com/for-sale/honda-jazz-hybrid-กรุงเทพและปริมณฑล-กาญจนาภิเษก/7254813"}