{"ราคา": "199,000 บาท", "ประเภท": "Sedan\n", "รูป": "https://img4.icarcdn.com/4167627/gallery_used-car-one2car-toyota-corolla-altis-g-sedan-thailand_4167627_BWaPsIlipNWdO7WGcGdZBE.jpg?smia=xTM", "\n\nดีลเลอร์มีความน่าเชื่อถือ ผ่านการตรวจสอบตามเกณฑ์ที่กำหนด\n": "ดีลเลอร์มีความน่าเชื่อถือ ผ่านการตรวจสอบตามเกณฑ์ที่กำหนด", "ยี่ห้อ": "Toyota", "รุ่น": "Corolla Altis", "โฉมรถยนต์": "(ปี 08-13)", "รายละเอียดรุ่น": "G", "ปี": "2010", "ขนาดเครื่องยนต์": "1598 ซีซี", "ระบบเกียร์": "เกียร์อัตโนมัติ", "จำนวนที่นั่ง": "5", "เลขไมล์ (กม.)": "0 - 5K", "สี": "สีเงิน", "สถานที่": "toyota-corolla-altis-g-กรุงเทพและปริมณฑล-กาญจนาภิเษก", "ลิงก์": "https://www.one2car.com/for-sale/toyota-corolla-altis-g-กรุงเทพและปริมณฑล-กาญจนาภิเษก/7267614"}